MANIFEST.in
README.md
requirements.txt
setup.cfg
setup.py
tests/__init__.py
tests/test_twisted_mtr.py
twisted_mtr/__init__.py
twisted_mtr/errors.py
twisted_mtr/logger.py
twisted_mtr/mtr.py
twisted_mtr/utils.py
twisted_mtr.egg-info/PKG-INFO
twisted_mtr.egg-info/SOURCES.txt
twisted_mtr.egg-info/dependency_links.txt
twisted_mtr.egg-info/requires.txt
twisted_mtr.egg-info/top_level.txt