Metadata-Version: 2.1
Name: twisted-mtr
Version: 3.1.1
Summary: Python Twisted library that performs high performanceasynchronous traceroutes using mtr-packet.
Home-page: https://github.com/meeb/twisted-mtr
Author: https://github.com/meeb
Author-email: meeb@meeb.org
License: BSD
Keywords: mtr,twisted,traceroute,async,asynchronous,trace,tracert,tx
Platform: UNKNOWN
Classifier: Development Status :: 5 - Production/Stable
Classifier: Environment :: Web Environment
Classifier: Intended Audience :: Developers
Classifier: License :: OSI Approved :: BSD License
Classifier: Operating System :: OS Independent
Classifier: Programming Language :: Python
Classifier: Programming Language :: Python :: 3
Classifier: Topic :: Software Development :: Libraries :: Python Modules
